{
  "timestamp": "2026-03-09T17:22:39.955606",
  "method": "Bootstrap resampling of tumor lineages with replacement",
  "n_bootstrap": 1000,
  "n_lineages": 20,
  "cv_threshold": 0.2,
  "all_stable": false,
  "weights": {
    "gini": {
      "observed_weight": 0.26,
      "bootstrap_mean": 0.2442,
      "bootstrap_median": 0.2675,
      "ci_95_low": 0.0221,
      "ci_95_high": 0.3949,
      "std": 0.1019,
      "cv": 0.4173,
      "stable": false,
      "ci_width": 0.3728
    },
    "selectivity": {
      "observed_weight": 0.2,
      "bootstrap_mean": 0.234,
      "bootstrap_median": 0.251,
      "ci_95_low": 0.0124,
      "ci_95_high": 0.4297,
      "std": 0.1169,
      "cv": 0.4993,
      "stable": false,
      "ci_width": 0.4173
    },
    "mean_pli": {
      "observed_weight": 0.36,
      "bootstrap_mean": 0.2677,
      "bootstrap_median": 0.2942,
      "ci_95_low": 0.0228,
      "ci_95_high": 0.4341,
      "std": 0.1082,
      "cv": 0.4041,
      "stable": false,
      "ci_width": 0.4112
    },
    "mean_centrality": {
      "observed_weight": 0.18,
      "bootstrap_mean": 0.254,
      "bootstrap_median": 0.2722,
      "ci_95_low": 0.0246,
      "ci_95_high": 0.3999,
      "std": 0.1008,
      "cv": 0.397,
      "stable": false,
      "ci_width": 0.3753
    }
  },
  "manuscript_text": " WARNING: some weights are unstable."
}